LICENSE
MANIFEST.in
README.md
setup.cfg
setup.py
src/net-snmp-5.7.3/.gitignore
src/net-snmp-5.7.3/AGENT.txt
src/net-snmp-5.7.3/CHANGES
src/net-snmp-5.7.3/COPYING
src/net-snmp-5.7.3/ChangeLog
src/net-snmp-5.7.3/CodingStyle
src/net-snmp-5.7.3/EXAMPLE.conf.def
src/net-snmp-5.7.3/FAQ
src/net-snmp-5.7.3/INSTALL
src/net-snmp-5.7.3/Makefile.am
src/net-snmp-5.7.3/Makefile.in
src/net-snmp-5.7.3/Makefile.rules
src/net-snmp-5.7.3/Makefile.top
src/net-snmp-5.7.3/NEWS
src/net-snmp-5.7.3/PORTING
src/net-snmp-5.7.3/README
src/net-snmp-5.7.3/README.Panasonic_AM3X.txt
src/net-snmp-5.7.3/README.agent-mibs
src/net-snmp-5.7.3/README.agentx
src/net-snmp-5.7.3/README.aix
src/net-snmp-5.7.3/README.hpux11
src/net-snmp-5.7.3/README.irix
src/net-snmp-5.7.3/README.krb5
src/net-snmp-5.7.3/README.osX
src/net-snmp-5.7.3/README.snmpv3
src/net-snmp-5.7.3/README.solaris
src/net-snmp-5.7.3/README.sql
src/net-snmp-5.7.3/README.thread
src/net-snmp-5.7.3/README.tru64
src/net-snmp-5.7.3/README.win32
src/net-snmp-5.7.3/TODO
src/net-snmp-5.7.3/acconfig.h
src/net-snmp-5.7.3/aclocal.m4
src/net-snmp-5.7.3/config.guess
src/net-snmp-5.7.3/config.sub
src/net-snmp-5.7.3/configure
src/net-snmp-5.7.3/configure.ac
src/net-snmp-5.7.3/dotgdbinit
src/net-snmp-5.7.3/doxygen.conf
src/net-snmp-5.7.3/install-sh
src/net-snmp-5.7.3/ltmain.sh
src/net-snmp-5.7.3/maketarget
src/net-snmp-5.7.3/mkinstalldirs
src/net-snmp-5.7.3/net-snmp-config.in
src/net-snmp-5.7.3/net-snmp-create-v3-user.in
src/net-snmp-5.7.3/sedscript.in
src/net-snmp-5.7.3/stamp-h.in
src/net-snmp-5.7.3/agent/Makefile.depend
src/net-snmp-5.7.3/agent/Makefile.in
src/net-snmp-5.7.3/agent/agent_handler.c
src/net-snmp-5.7.3/agent/agent_index.c
src/net-snmp-5.7.3/agent/agent_read_config.c
src/net-snmp-5.7.3/agent/agent_registry.c
src/net-snmp-5.7.3/agent/agent_sysORTable.c
src/net-snmp-5.7.3/agent/agent_trap.c
src/net-snmp-5.7.3/agent/auto_nlist.c
src/net-snmp-5.7.3/agent/autonlist.h
src/net-snmp-5.7.3/agent/kernel.c
src/net-snmp-5.7.3/agent/kernel.h
yahoo_panoptes_snmp.egg-info/PKG-INFO
yahoo_panoptes_snmp.egg-info/SOURCES.txt
yahoo_panoptes_snmp.egg-info/dependency_links.txt
yahoo_panoptes_snmp.egg-info/requires.txt
yahoo_panoptes_snmp.egg-info/top_level.txt