Metadata-Version: 2.1
Name: yahoo-panoptes-snmp
Version: 0.2.5.115
Summary: A Python wrapper on Net-SNMP
Home-page: https://github.com/yahoo/panoptes_snmp
Author: Network Automation @ Oath, Inc.
Author-email: network-automation@oath.com
License: BSD
Platform: UNKNOWN
Classifier: Development Status :: 4 - Beta
Classifier: Intended Audience :: Developers
Classifier: License :: OSI Approved :: BSD License
Classifier: Operating System :: OS Independent
Classifier: Programming Language :: Python
Classifier: Programming Language :: Python :: 2.7
Classifier: Topic :: System :: Networking
Classifier: Topic :: System :: Networking :: Monitoring
